LICENSE
MANIFEST.in
NOTICE
README.md
requirements.txt
setup.py
tile_generator/__init__.py
tile_generator/bosh.py
tile_generator/bosh_unittest.py
tile_generator/build.py
tile_generator/build_unittest.py
tile_generator/config.py
tile_generator/config_unittest.py
tile_generator/erb.py
tile_generator/helm.py
tile_generator/helm_unittest.py
tile_generator/opsmgr.py
tile_generator/opsmgr_unittest.py
tile_generator/package_definitions.py
tile_generator/package_flags.py
tile_generator/package_flags_unittest.py
tile_generator/pcf.py
tile_generator/pcf_unittest.py
tile_generator/template.py
tile_generator/template_unittest.py
tile_generator/tile.py
tile_generator/tile_metadata.py
tile_generator/tile_metadata_unittest.py
tile_generator/tile_unittest.py
tile_generator/util.py
tile_generator/version.py
tile_generator.egg-info/PKG-INFO
tile_generator.egg-info/SOURCES.txt
tile_generator.egg-info/dependency_links.txt
tile_generator.egg-info/entry_points.txt
tile_generator.egg-info/requires.txt
tile_generator.egg-info/top_level.txt
tile_generator/templates/gitignore
tile_generator/templates/tile.yml
tile_generator/templates/config/blobs.yml
tile_generator/templates/config/final.yml
tile_generator/templates/jobs/charts_to_disk.sh.erb
tile_generator/templates/jobs/delete-all.sh.erb
tile_generator/templates/jobs/delete-charts.sh.erb
tile_generator/templates/jobs/deploy-all.sh.erb
tile_generator/templates/jobs/deploy-charts.sh.erb
tile_generator/templates/jobs/docker-bosh.sh.erb
tile_generator/templates/jobs/monit
tile_generator/templates/jobs/opsmgr.env.erb
tile_generator/templates/jobs/spec
tile_generator/templates/packages/packaging
tile_generator/templates/packages/spec
tile_generator/templates/src/common/utils.sh
tile_generator/templates/src/templates/all_open.json
tile_generator/templates/tile/metadata.yml
tile_generator/templates/tile/migration.js