Metadata-Version: 2.1
Name: tile-generator
Version: 14.0.6
Summary: Tools supporting development of Pivotal Cloud Foundry services and add-ons.
Home-page: https://github.com/cf-platform-eng/tile-generator
Author: Pivotal Cloud Foundry Platform Engineering
License: Apache 2.0
Keywords: pivotal cloud foundry,tile,generator
Platform: UNKNOWN
Classifier: Development Status :: 4 - Beta
Classifier: Environment :: Console
Classifier: Intended Audience :: Developers
Classifier: License :: OSI Approved :: Apache Software License
Classifier: Programming Language :: Python :: 3 :: Only
Classifier: Topic :: Software Development
Classifier: Topic :: Software Development :: Code Generators
